[
	{
		"title": "Types",
		"description": "Types are building blocks for module forms",
		"package": "crm",
		"entrypoint": "types",
		"path": "types",
		"authentication": [],
		"struct": [],
		"apis": [
			{
				"name": "list",
				"method": "GET",
				"title": "List available types"
			},
			{
				"name": "type",
				"path": "/type/{id}",
				"method": "GET",
				"title": "Get type details",
				"parameters": {
					"path": [
						{ "type": "string", "name": "id", "required": true, "title": "Type ID" }
					]
				}
			}
		]
	},
	{
		"title": "Modules",
		"description": "CRM module definitions",
		"package": "crm",
		"entrypoint": "module",
		"path": "module",
		"authentication": [],
		"struct": [
			{
				"name": "Module",
				"fields": [
					{ "name": "ID", "type": "uint64" },
					{ "name": "Name", "type": "string" }
				]
			}
		],
		"apis": [
			{
				"name": "list",
				"method": "GET",
				"title": "List defined modules",
				"parameters": {
					"get": [
						{ "type": "string", "name": "id", "title": "Module ID" }
					]
				}
			},
			{
				"name": "edit",
				"method": "POST",
				"title": "Add/edit module",
				"parameters": {
					"post": [
						{ "type": "uint64", "name": "id", "required": false, "title": "Module ID" },
						{ "type": "string", "name": "name", "required": true, "title": "Module Name" }
					]
				}
			},
			{
				"name": "content/list",
				"method": "GET",
				"title": "List/read contents from module section",
				"parameters": {
					"get": [
						{ "type": "string", "name": "id", "title": "Module ID" }
					]
				}
			},
			{
				"name": "content/edit",
				"method": "POST",
				"title": "Add/update contents in module section",
				"parameters": {
					"post": [
						{ "type": "uint64", "name": "id", "required": false, "title": "Content ID" },
						{ "type": "string", "name": "payload", "required": true, "title": "Content JSON" }
					]
				}
			},
			{
				"name": "content/delete",
				"method": "DELETE",
				"title": "Delete content row from module section",
				"parameters": {
					"post": [
						{ "type": "uint64", "name": "id", "required": true, "title": "Content ID" }
					]
				}
			}
		]
	}
]